Metadata-Version: 1.1
Name: prospero
Version: 0.5
Summary: Prospero - RESTful Datastore
Home-page: http://pypi.python.org/pypi/prospero
Author: numero
Author-email: hi@theothernumber.com
License: Apache License, Version 2.0
Keywords: mongo,tornado,REST
Platform: UNKNOWN
Classifier: Development Status :: 4 - Beta
Classifier: License :: OSI Approved :: Apache Software License
Classifier: Environment :: Console
Classifier: Environment :: Web Environment
Classifier: Intended Audience :: Developers
Classifier: Intended Audience :: System Administrators
Classifier: Operating System :: MacOS :: MacOS X
Classifier: Operating System :: Microsoft :: Windows
Classifier: Operating System :: POSIX
Classifier: Programming Language :: Python
Requires: pymongo (>=1.52)
Requires: simplejson (>=2.1.0)
Requires: tornado (>=0.2)
Requires: amfast (>=0.5.1)
Requires: pygments (>=1.3.1)
